zemath/__init__.py
zemath/zemath.py
zemath-0.1.dist-info/LICENSE
zemath-0.1.dist-info/METADATA
zemath-0.1.dist-info/WHEEL
zemath-0.1.dist-info/top_level.txt
zemath-0.1.dist-info/RECORD
