Metadata-Version: 2.1
Name: zemath
Version: 0.1
Summary: It's a simple python module to handle basic math
Author-email: Mohammed Musthafa A <mohammed.musthafa.dev@gmail.com>
License: MIT License
Project-URL: Homepage, https://github.com/zandora-space/
Project-URL: Bug Tracker, https://github.com/zandora-space/
Classifier: Programming Language :: Python :: 3
Classifier: License :: OSI Approved :: MIT License
Classifier: Operating System :: OS Independent
Requires-Python: >=3.7
License-File: LICENSE
